spidr/__init__.py
spidr/__main__.py
spidr/checkpoint.py
spidr/config.py
spidr/environment.py
spidr/optimizer.py
spidr/slurm.py
spidr/train.py
spidr/validate.py
spidr/data/__init__.py
spidr/data/dataset.py
spidr/data/masks.py
spidr/data/utils.py
spidr/data/write_manifest.py
spidr/models/__init__.py
spidr/models/components.py
spidr/models/dinosr.py
spidr/models/metrics.py
spidr/models/spidr.py
spidr/models/utils.py
spidr/tools/__init__.py
spidr/tools/git.py
spidr/tools/logger.py
spidr/tools/meters.py
spidr/tools/metrics_queue.py
spidr/tools/profiler.py
spidr-0.1.2.dist-info/licenses/LICENSE
spidr-0.1.2.dist-info/WHEEL
spidr-0.1.2.dist-info/METADATA
spidr-0.1.2.dist-info/RECORD
