Metadata-Version: 2.4
Name: spidr
Version: 0.1.2
Summary: Learning Fast and Stable Linguistic Units for Spoken Language Models Without Supervision
Keywords: machine learning,speech
Author: Fundamental AI Research (FAIR) at Meta
Requires-Python: >=3.12
License-Expression: CC-BY-NC-4.0
Classifier: Development Status :: 5 - Production/Stable
Classifier: Intended Audience :: Science/Research
Classifier: Operating System :: OS Independent
Classifier: Programming Language :: Python :: 3 :: Only
Classifier: Programming Language :: Python :: 3.12
Classifier: Programming Language :: Python :: 3.13
Classifier: Topic :: Scientific/Engineering
Classifier: Topic :: Scientific/Engineering :: Artificial Intelligence
License-File: LICENSE
Requires-Dist: numpy>=1.26.4
Requires-Dist: torch>=2.8.0
Requires-Dist: fastabx>=0.5.2 ; extra == "plot"
Requires-Dist: matplotlib>=3.10.3 ; extra == "plot"
Requires-Dist: polars>=1.31.0 ; extra == "plot"
Requires-Dist: scikit-learn>=1.7.0 ; extra == "plot"
Requires-Dist: scipy>=1.16.0 ; extra == "plot"
Requires-Dist: torchcodec>=0.6.0 ; extra == "plot"
Requires-Dist: polars>=1.31.0 ; extra == "train"
Requires-Dist: submitit>=1.5.2 ; extra == "train"
Requires-Dist: torchcodec>=0.7.0 ; extra == "train"
Requires-Dist: tqdm>=4.67.1 ; extra == "train"
Requires-Dist: viztracer>=1.0.3 ; extra == "train"
Requires-Dist: wandb>=0.19.10 ; extra == "train"
Project-URL: github, https://github.com/facebookresearch/spidr
Provides-Extra: plot
Provides-Extra: train
